odoo_module_migrate/__init__.py
odoo_module_migrate/__main__.py
odoo_module_migrate/base_migration_script.py
odoo_module_migrate/config.py
odoo_module_migrate/exception.py
odoo_module_migrate/log.py
odoo_module_migrate/migration.py
odoo_module_migrate/module_migration.py
odoo_module_migrate/tools.py
odoo_module_migrate/migration_scripts/__init__.py
odoo_module_migrate/migration_scripts/migrate_080_090.py
odoo_module_migrate/migration_scripts/migrate_080_allways.py
odoo_module_migrate/migration_scripts/migrate_090_100.py
odoo_module_migrate/migration_scripts/migrate_100_110.py
odoo_module_migrate/migration_scripts/migrate_100_allways.py
odoo_module_migrate/migration_scripts/migrate_110_120.py
odoo_module_migrate/migration_scripts/migrate_120_130.py
odoo_module_migrate/migration_scripts/migrate_130_140.py
odoo_module_migrate/migration_scripts/migrate_140_150.py
odoo_module_migrate/migration_scripts/migrate_150_160.py
odoo_module_migrate/migration_scripts/migrate_allways.py
odoo_module_migrate/migration_scripts/migrate_remove_migration_folder.py
odoo_module_migrate/migration_scripts/deprecated_modules/migrate_080_090/account_modules.yaml
odoo_module_migrate/migration_scripts/python_scripts/migrate_allways/bump_version.py
odoo_module_migrate/migration_scripts/removed_fields/migrate_150_160/product.yaml
odoo_module_migrate/migration_scripts/renamed_fields/migrate_150_160/account.yaml
odoo_module_migrate/migration_scripts/text_errors/migrate_100_110/unexisted_models.yaml
odoo_module_migrate/migration_scripts/text_errors/migrate_150_160/orm_methods.yaml
odoo_module_migrate/migration_scripts/text_replaces/migrate_120_130/decorators.yaml
odoo_module_migrate/migration_scripts/text_replaces/migrate_120_130/digits_precision.yaml
odoo_module_migrate/migration_scripts/text_warnings/migrate_120_130/company.yaml
odoo_module_migrate/migration_scripts/text_warnings/migrate_150_160/orm_methods.yaml
odoo_module_migrator-0.4.0.dist-info/LICENSE
odoo_module_migrator-0.4.0.dist-info/METADATA
odoo_module_migrator-0.4.0.dist-info/WHEEL
odoo_module_migrator-0.4.0.dist-info/entry_points.txt
odoo_module_migrator-0.4.0.dist-info/top_level.txt
odoo_module_migrator-0.4.0.dist-info/RECORD
