Metadata-Version: 2.1
Name: odoo-module-migrator
Version: 0.4.0
Summary: Small tools to migrate Odoo modules from a version to another
Home-page: https://github.com/OCA/odoo-module-migrator
Author: GRAP, Groupement Régional Alimentaire de Proximité
Author-email: informatique@grap.coop
Keywords: Odoo Community Association (OCA),Odoo,Migration,Upgrade,Module
Classifier: Development Status :: 3 - Alpha
Classifier: Framework :: Odoo
Classifier: Topic :: Software Development :: Code Generators
Classifier: Programming Language :: Python :: 3
Classifier: License :: OSI Approved :: GNU Affero General Public License v3
Classifier: Environment :: Console
License-File: LICENSE
